mpl_scatter_density/__init__.py
mpl_scatter_density/base_image_artist.py
mpl_scatter_density/color.py
mpl_scatter_density/fixed_data_density_helper.py
mpl_scatter_density/generic_density_artist.py
mpl_scatter_density/scatter_density_artist.py
mpl_scatter_density/scatter_density_axes.py
mpl_scatter_density/tests/__init__.py
mpl_scatter_density/tests/test_base_image_artist.py
mpl_scatter_density/tests/test_scatter_density_artist.py
mpl_scatter_density/tests/test_scatter_density_axes.py
mpl_scatter_density/tests/baseline/2.0.x/test_axes_basic.png
mpl_scatter_density/tests/baseline/2.0.x/test_axes_projection.png
mpl_scatter_density/tests/baseline/2.0.x/test_color.png
mpl_scatter_density/tests/baseline/2.0.x/test_colorcode.png
mpl_scatter_density/tests/baseline/2.0.x/test_colorcode_downres.png
mpl_scatter_density/tests/baseline/2.0.x/test_default.png
mpl_scatter_density/tests/baseline/2.0.x/test_downres_False.png
mpl_scatter_density/tests/baseline/2.0.x/test_downres_True.png
mpl_scatter_density/tests/baseline/2.0.x/test_flipping_False-False.png
mpl_scatter_density/tests/baseline/2.0.x/test_flipping_False-True.png
mpl_scatter_density/tests/baseline/2.0.x/test_flipping_True-False.png
mpl_scatter_density/tests/baseline/2.0.x/test_flipping_True-True.png
mpl_scatter_density/tests/baseline/2.0.x/test_image_settings.png
mpl_scatter_density/tests/baseline/2.0.x/test_manual_limits.png
mpl_scatter_density/tests/baseline/2.0.x/test_multi_scatter.png
mpl_scatter_density/tests/baseline/2.0.x/test_norm.png
mpl_scatter_density/tests/baseline/2.0.x/test_origin.png
mpl_scatter_density/tests/baseline/2.0.x/test_remove.png
mpl_scatter_density/tests/baseline/2.0.x/test_scales_linear-linear.png
mpl_scatter_density/tests/baseline/2.0.x/test_scales_linear-log.png
mpl_scatter_density/tests/baseline/2.0.x/test_scales_log-linear.png
mpl_scatter_density/tests/baseline/2.0.x/test_scales_log-log.png
mpl_scatter_density-0.7.dist-info/LICENSE
mpl_scatter_density-0.7.dist-info/METADATA
mpl_scatter_density-0.7.dist-info/WHEEL
mpl_scatter_density-0.7.dist-info/top_level.txt
mpl_scatter_density-0.7.dist-info/zip-safe
mpl_scatter_density-0.7.dist-info/RECORD
