Metadata-Version: 2.1
Name: mpl-scatter-density
Version: 0.7
Summary: Matplotlib helpers to make density scatter plots
Home-page: https://github.com/astrofrog/mpl-scatter-density
Author: Thomas Robitaille
Author-email: thomas.robitaille@gmail.com
License: BSD
Platform: UNKNOWN
Requires-Python: >=3.6
Provides-Extra: test
